zaigonhack/__init__.py
zaigonhack/courses.py
zaigonhack/utils.py
zaigonhack-0.5.0.dist-info/METADATA
zaigonhack-0.5.0.dist-info/WHEEL
zaigonhack-0.5.0.dist-info/top_level.txt
zaigonhack-0.5.0.dist-info/RECORD
